mini_trainer/__init__.py
mini_trainer/templates.py
mini_trainer/trainer.py
mini_trainer/utils.py
mini_trainer/extensions/__init__.py
mini_trainer/extensions/base.py
mini_trainer/extensions/core/__init__.py
mini_trainer/extensions/core/accelerate.py
mini_trainer/extensions/core/checkpoint.py
mini_trainer/extensions/core/early_stopping.py
mini_trainer/extensions/core/loss_plot.py
mini_trainer/extensions/core/lr_scheduler.py
mini_trainer/extensions/core/profiler.py
mini_trainer/extensions/core/progbar.py
mini_trainer-0.2.3.dist-info/LICENSE
mini_trainer-0.2.3.dist-info/METADATA
mini_trainer-0.2.3.dist-info/WHEEL
mini_trainer-0.2.3.dist-info/top_level.txt
mini_trainer-0.2.3.dist-info/RECORD
