Metadata-Version: 2.1
Name: mini-trainer
Version: 0.2.3
Summary: The PyTorch micro framework for training neural networks.
Home-page: https://github.com/liaoyuhua/mini-trainer
Author: liaoyuhua
Author-email: ml.liaoyuhua@gmail.com
Classifier: Programming Language :: Python :: 3
Classifier: License :: OSI Approved :: MIT License
Classifier: Operating System :: OS Independent
Requires-Python: >=3.9
License-File: LICENSE
Requires-Dist: torch ~=2.2.0
Requires-Dist: tqdm ~=4.66.2
Requires-Dist: numpy ~=1.26.4
Requires-Dist: matplotlib ~=3.8.3
